nexusai/__init__.py
nexusai/__version__.py
nexusai/_internal/__init__.py
nexusai/_internal/_client.py
nexusai/_internal/_poller.py
nexusai/_internal/_retry.py
nexusai/client.py
nexusai/config.py
nexusai/constants.py
nexusai/error.py
nexusai/models/__init__.py
nexusai/models/embedding.py
nexusai/resources/__init__.py
nexusai/resources/audio.py
nexusai/resources/embeddings.py
nexusai/resources/files.py
nexusai/resources/images.py
nexusai/resources/knowledge_bases.py
nexusai/resources/sessions.py
nexusai/resources/text.py
nexusai/types.py
keystone_ai-0.2.3.dist-info/licenses/LICENSE
keystone_ai-0.2.3.dist-info/METADATA
keystone_ai-0.2.3.dist-info/WHEEL
keystone_ai-0.2.3.dist-info/RECORD
