Metadata-Version: 2.4
Name: keystone-ai
Version: 0.2.3
Summary: Python SDK for Nexus AI Platform - Complete text embedding & RAG capabilities
License: MIT
License-File: LICENSE
Keywords: ai,api,sdk,nexus,openai,llm
Author: Nexus AI Team
Author-email: support@nexus-ai.com
Requires-Python: >=3.8,<4.0
Classifier: Development Status :: 4 - Beta
Classifier: Intended Audience :: Developers
Classifier: License :: OSI Approved :: MIT License
Classifier: Operating System :: OS Independent
Classifier: Programming Language :: Python :: 3
Classifier: Programming Language :: Python :: 3.8
Classifier: Programming Language :: Python :: 3.9
Classifier: Programming Language :: Python :: 3.10
Classifier: Programming Language :: Python :: 3.11
Classifier: Programming Language :: Python :: 3.12
Classifier: Programming Language :: Python :: 3.13
Classifier: Programming Language :: Python :: 3.14
Classifier: Topic :: Scientific/Engineering :: Artificial Intelligence
Classifier: Topic :: Software Development :: Libraries :: Python Modules
Classifier: Typing :: Typed
Requires-Dist: httpx (>=0.25.0,<0.26.0)
Requires-Dist: pydantic (>=2.5.0,<3.0.0)
Requires-Dist: python-dotenv (>=1.0.0,<2.0.0)
Requires-Dist: typing-extensions (>=4.8.0,<5.0.0)
Project-URL: Homepage, https://nexus-ai.juncai-ai.com
Project-URL: Repository, https://github.com/aidrshao/nexus-ai-sdk
